braintrust_core/__init__.py
braintrust_core/score.py
braintrust_core/serializable_data_class.py
braintrust_core/test_serializable_data_class.py
braintrust_core/version.py
braintrust_core-0.0.59.dist-info/METADATA
braintrust_core-0.0.59.dist-info/WHEEL
braintrust_core-0.0.59.dist-info/top_level.txt
braintrust_core-0.0.59.dist-info/RECORD
