Metadata-Version: 2.4
Name: braintrust_core
Version: 0.0.59
Summary: Shared core dependencies for Braintrust packages
Home-page: https://www.braintrust.dev
Author: Braintrust
Author-email: info@braintrust.dev
Classifier: Programming Language :: Python :: 3
Classifier: Operating System :: OS Independent
Requires-Python: >=3.8.0
Dynamic: author
Dynamic: author-email
Dynamic: classifier
Dynamic: description
Dynamic: description-content-type
Dynamic: home-page
Dynamic: requires-python
Dynamic: summary
